{
  "version": "5",
  "dialect": "mysql",
  "id": "d261b9ed-a10e-4c6e-89e3-4955349f163b",
  "prevId": "cc0da05f-c592-4b5f-8994-7b317b6dc46e",
  "tables": {
    "alerts": {
      "name": "alerts",
      "columns": {
        "id": {
          "name": "id",
          "type": "int",
          "primaryKey": false,
          "notNull": true,
          "autoincrement": true
        },
        "userId": {
          "name": "userId",
          "type": "int",
          "primaryKey": false,
          "notNull": true,
          "autoincrement": false
        },
        "type": {
          "name": "type",
          "type": "enum('high_risk','opportunity','macro_change','model_drift','system')",
          "primaryKey": false,
          "notNull": true,
          "autoincrement": false
        },
        "severity": {
          "name": "severity",
          "type": "enum('info','warning','critical')",
          "primaryKey": false,
          "notNull": true,
          "autoincrement": false,
          "default": "'info'"
        },
        "title": {
          "name": "title",
          "type": "varchar(255)",
          "primaryKey": false,
          "notNull": true,
          "autoincrement": false
        },
        "message": {
          "name": "message",
          "type": "text",
          "primaryKey": false,
          "notNull": true,
          "autoincrement": false
        },
        "isRead": {
          "name": "isRead",
          "type": "boolean",
          "primaryKey": false,
          "notNull": true,
          "autoincrement": false,
          "default": false
        },
        "metadata": {
          "name": "metadata",
          "type": "json",
          "primaryKey": false,
          "notNull": false,
          "autoincrement": false
        },
        "createdAt": {
          "name": "createdAt",
          "type": "timestamp",
          "primaryKey": false,
          "notNull": true,
          "autoincrement": false,
          "default": "(now())"
        }
      },
      "indexes": {},
      "foreignKeys": {},
      "compositePrimaryKeys": {
        "alerts_id": {
          "name": "alerts_id",
          "columns": [
            "id"
          ]
        }
      },
      "uniqueConstraints": {},
      "checkConstraint": {}
    },
    "deals": {
      "name": "deals",
      "columns": {
        "id": {
          "name": "id",
          "type": "int",
          "primaryKey": false,
          "notNull": true,
          "autoincrement": true
        },
        "userId": {
          "name": "userId",
          "type": "int",
          "primaryKey": false,
          "notNull": true,
          "autoincrement": false
        },
        "name": {
          "name": "name",
          "type": "varchar(255)",
          "primaryKey": false,
          "notNull": true,
          "autoincrement": false
        },
        "sector": {
          "name": "sector",
          "type": "varchar(64)",
          "primaryKey": false,
          "notNull": false,
          "autoincrement": false
        },
        "status": {
          "name": "status",
          "type": "enum('active','monitoring','exited','watchlist')",
          "primaryKey": false,
          "notNull": true,
          "autoincrement": false,
          "default": "'active'"
        },
        "predictionId": {
          "name": "predictionId",
          "type": "int",
          "primaryKey": false,
          "notNull": false,
          "autoincrement": false
        },
        "notes": {
          "name": "notes",
          "type": "text",
          "primaryKey": false,
          "notNull": false,
          "autoincrement": false
        },
        "investmentAmount": {
          "name": "investmentAmount",
          "type": "decimal(18,2)",
          "primaryKey": false,
          "notNull": false,
          "autoincrement": false
        },
        "currency": {
          "name": "currency",
          "type": "varchar(8)",
          "primaryKey": false,
          "notNull": false,
          "autoincrement": false,
          "default": "'KES'"
        },
        "createdAt": {
          "name": "createdAt",
          "type": "timestamp",
          "primaryKey": false,
          "notNull": true,
          "autoincrement": false,
          "default": "(now())"
        },
        "updatedAt": {
          "name": "updatedAt",
          "type": "timestamp",
          "primaryKey": false,
          "notNull": true,
          "autoincrement": false,
          "onUpdate": true,
          "default": "(now())"
        }
      },
      "indexes": {},
      "foreignKeys": {},
      "compositePrimaryKeys": {
        "deals_id": {
          "name": "deals_id",
          "columns": [
            "id"
          ]
        }
      },
      "uniqueConstraints": {},
      "checkConstraint": {}
    },
    "macroCache": {
      "name": "macroCache",
      "columns": {
        "id": {
          "name": "id",
          "type": "int",
          "primaryKey": false,
          "notNull": true,
          "autoincrement": true
        },
        "indicator": {
          "name": "indicator",
          "type": "varchar(64)",
          "primaryKey": false,
          "notNull": true,
          "autoincrement": false
        },
        "value": {
          "name": "value",
          "type": "float",
          "primaryKey": false,
          "notNull": true,
          "autoincrement": false
        },
        "source": {
          "name": "source",
          "type": "varchar(64)",
          "primaryKey": false,
          "notNull": false,
          "autoincrement": false
        },
        "fetchedAt": {
          "name": "fetchedAt",
          "type": "timestamp",
          "primaryKey": false,
          "notNull": true,
          "autoincrement": false,
          "default": "(now())"
        }
      },
      "indexes": {},
      "foreignKeys": {},
      "compositePrimaryKeys": {
        "macroCache_id": {
          "name": "macroCache_id",
          "columns": [
            "id"
          ]
        }
      },
      "uniqueConstraints": {
        "macroCache_indicator_unique": {
          "name": "macroCache_indicator_unique",
          "columns": [
            "indicator"
          ]
        }
      },
      "checkConstraint": {}
    },
    "portfolios": {
      "name": "portfolios",
      "columns": {
        "id": {
          "name": "id",
          "type": "int",
          "primaryKey": false,
          "notNull": true,
          "autoincrement": true
        },
        "userId": {
          "name": "userId",
          "type": "int",
          "primaryKey": false,
          "notNull": true,
          "autoincrement": false
        },
        "name": {
          "name": "name",
          "type": "varchar(255)",
          "primaryKey": false,
          "notNull": true,
          "autoincrement": false
        },
        "description": {
          "name": "description",
          "type": "text",
          "primaryKey": false,
          "notNull": false,
          "autoincrement": false
        },
        "totalCompanies": {
          "name": "totalCompanies",
          "type": "int",
          "primaryKey": false,
          "notNull": true,
          "autoincrement": false,
          "default": 0
        },
        "avgRisk": {
          "name": "avgRisk",
          "type": "float",
          "primaryKey": false,
          "notNull": false,
          "autoincrement": false
        },
        "portfolioIrr": {
          "name": "portfolioIrr",
          "type": "float",
          "primaryKey": false,
          "notNull": false,
          "autoincrement": false
        },
        "totalAum": {
          "name": "totalAum",
          "type": "decimal(18,2)",
          "primaryKey": false,
          "notNull": false,
          "autoincrement": false
        },
        "currency": {
          "name": "currency",
          "type": "varchar(8)",
          "primaryKey": false,
          "notNull": false,
          "autoincrement": false,
          "default": "'KES'"
        },
        "createdAt": {
          "name": "createdAt",
          "type": "timestamp",
          "primaryKey": false,
          "notNull": true,
          "autoincrement": false,
          "default": "(now())"
        },
        "updatedAt": {
          "name": "updatedAt",
          "type": "timestamp",
          "primaryKey": false,
          "notNull": true,
          "autoincrement": false,
          "onUpdate": true,
          "default": "(now())"
        }
      },
      "indexes": {},
      "foreignKeys": {},
      "compositePrimaryKeys": {
        "portfolios_id": {
          "name": "portfolios_id",
          "columns": [
            "id"
          ]
        }
      },
      "uniqueConstraints": {},
      "checkConstraint": {}
    },
    "predictions": {
      "name": "predictions",
      "columns": {
        "id": {
          "name": "id",
          "type": "int",
          "primaryKey": false,
          "notNull": true,
          "autoincrement": true
        },
        "userId": {
          "name": "userId",
          "type": "int",
          "primaryKey": false,
          "notNull": true,
          "autoincrement": false
        },
        "gdpGrowth": {
          "name": "gdpGrowth",
          "type": "float",
          "primaryKey": false,
          "notNull": true,
          "autoincrement": false
        },
        "inflation": {
          "name": "inflation",
          "type": "float",
          "primaryKey": false,
          "notNull": true,
          "autoincrement": false
        },
        "revenueGrowth": {
          "name": "revenueGrowth",
          "type": "float",
          "primaryKey": false,
          "notNull": true,
          "autoincrement": false
        },
        "debtRatio": {
          "name": "debtRatio",
          "type": "float",
          "primaryKey": false,
          "notNull": true,
          "autoincrement": false
        },
        "volatility": {
          "name": "volatility",
          "type": "float",
          "primaryKey": false,
          "notNull": true,
          "autoincrement": false
        },
        "sector": {
          "name": "sector",
          "type": "varchar(64)",
          "primaryKey": false,
          "notNull": false,
          "autoincrement": false
        },
        "dealName": {
          "name": "dealName",
          "type": "varchar(255)",
          "primaryKey": false,
          "notNull": false,
          "autoincrement": false
        },
        "riskScore": {
          "name": "riskScore",
          "type": "float",
          "primaryKey": false,
          "notNull": true,
          "autoincrement": false
        },
        "predictedIrr": {
          "name": "predictedIrr",
          "type": "float",
          "primaryKey": false,
          "notNull": true,
          "autoincrement": false
        },
        "confidence": {
          "name": "confidence",
          "type": "float",
          "primaryKey": false,
          "notNull": false,
          "autoincrement": false,
          "default": 0.85
        },
        "riskLabel": {
          "name": "riskLabel",
          "type": "varchar(32)",
          "primaryKey": false,
          "notNull": false,
          "autoincrement": false
        },
        "riskAdjustedReturn": {
          "name": "riskAdjustedReturn",
          "type": "float",
          "primaryKey": false,
          "notNull": false,
          "autoincrement": false
        },
        "sharpeProxy": {
          "name": "sharpeProxy",
          "type": "float",
          "primaryKey": false,
          "notNull": false,
          "autoincrement": false
        },
        "shapValues": {
          "name": "shapValues",
          "type": "json",
          "primaryKey": false,
          "notNull": false,
          "autoincrement": false
        },
        "modelVersion": {
          "name": "modelVersion",
          "type": "varchar(32)",
          "primaryKey": false,
          "notNull": false,
          "autoincrement": false,
          "default": "'1.0.0'"
        },
        "isBatch": {
          "name": "isBatch",
          "type": "boolean",
          "primaryKey": false,
          "notNull": true,
          "autoincrement": false,
          "default": false
        },
        "createdAt": {
          "name": "createdAt",
          "type": "timestamp",
          "primaryKey": false,
          "notNull": true,
          "autoincrement": false,
          "default": "(now())"
        }
      },
      "indexes": {},
      "foreignKeys": {},
      "compositePrimaryKeys": {
        "predictions_id": {
          "name": "predictions_id",
          "columns": [
            "id"
          ]
        }
      },
      "uniqueConstraints": {},
      "checkConstraint": {}
    },
    "subscriptions": {
      "name": "subscriptions",
      "columns": {
        "id": {
          "name": "id",
          "type": "int",
          "primaryKey": false,
          "notNull": true,
          "autoincrement": true
        },
        "userId": {
          "name": "userId",
          "type": "int",
          "primaryKey": false,
          "notNull": true,
          "autoincrement": false
        },
        "tier": {
          "name": "tier",
          "type": "enum('free','pro','enterprise')",
          "primaryKey": false,
          "notNull": true,
          "autoincrement": false,
          "default": "'free'"
        },
        "stripeCustomerId": {
          "name": "stripeCustomerId",
          "type": "varchar(255)",
          "primaryKey": false,
          "notNull": false,
          "autoincrement": false
        },
        "stripeSubscriptionId": {
          "name": "stripeSubscriptionId",
          "type": "varchar(255)",
          "primaryKey": false,
          "notNull": false,
          "autoincrement": false
        },
        "status": {
          "name": "status",
          "type": "enum('active','cancelled','past_due','trialing')",
          "primaryKey": false,
          "notNull": true,
          "autoincrement": false,
          "default": "'active'"
        },
        "currentPeriodStart": {
          "name": "currentPeriodStart",
          "type": "timestamp",
          "primaryKey": false,
          "notNull": false,
          "autoincrement": false
        },
        "currentPeriodEnd": {
          "name": "currentPeriodEnd",
          "type": "timestamp",
          "primaryKey": false,
          "notNull": false,
          "autoincrement": false
        },
        "createdAt": {
          "name": "createdAt",
          "type": "timestamp",
          "primaryKey": false,
          "notNull": true,
          "autoincrement": false,
          "default": "(now())"
        },
        "updatedAt": {
          "name": "updatedAt",
          "type": "timestamp",
          "primaryKey": false,
          "notNull": true,
          "autoincrement": false,
          "onUpdate": true,
          "default": "(now())"
        }
      },
      "indexes": {},
      "foreignKeys": {},
      "compositePrimaryKeys": {
        "subscriptions_id": {
          "name": "subscriptions_id",
          "columns": [
            "id"
          ]
        }
      },
      "uniqueConstraints": {
        "subscriptions_userId_unique": {
          "name": "subscriptions_userId_unique",
          "columns": [
            "userId"
          ]
        }
      },
      "checkConstraint": {}
    },
    "users": {
      "name": "users",
      "columns": {
        "id": {
          "name": "id",
          "type": "int",
          "primaryKey": false,
          "notNull": true,
          "autoincrement": true
        },
        "openId": {
          "name": "openId",
          "type": "varchar(64)",
          "primaryKey": false,
          "notNull": true,
          "autoincrement": false
        },
        "name": {
          "name": "name",
          "type": "text",
          "primaryKey": false,
          "notNull": false,
          "autoincrement": false
        },
        "email": {
          "name": "email",
          "type": "varchar(320)",
          "primaryKey": false,
          "notNull": false,
          "autoincrement": false
        },
        "loginMethod": {
          "name": "loginMethod",
          "type": "varchar(64)",
          "primaryKey": false,
          "notNull": false,
          "autoincrement": false
        },
        "role": {
          "name": "role",
          "type": "enum('analyst','investor','admin')",
          "primaryKey": false,
          "notNull": true,
          "autoincrement": false,
          "default": "'analyst'"
        },
        "firm": {
          "name": "firm",
          "type": "varchar(255)",
          "primaryKey": false,
          "notNull": false,
          "autoincrement": false
        },
        "language": {
          "name": "language",
          "type": "enum('en','sw')",
          "primaryKey": false,
          "notNull": true,
          "autoincrement": false,
          "default": "'en'"
        },
        "darkMode": {
          "name": "darkMode",
          "type": "boolean",
          "primaryKey": false,
          "notNull": true,
          "autoincrement": false,
          "default": false
        },
        "tier": {
          "name": "tier",
          "type": "enum('free','pro','enterprise')",
          "primaryKey": false,
          "notNull": true,
          "autoincrement": false,
          "default": "'free'"
        },
        "predictionsUsed": {
          "name": "predictionsUsed",
          "type": "int",
          "primaryKey": false,
          "notNull": true,
          "autoincrement": false,
          "default": 0
        },
        "predictionsResetAt": {
          "name": "predictionsResetAt",
          "type": "timestamp",
          "primaryKey": false,
          "notNull": true,
          "autoincrement": false,
          "default": "(now())"
        },
        "notifyEmail": {
          "name": "notifyEmail",
          "type": "boolean",
          "primaryKey": false,
          "notNull": true,
          "autoincrement": false,
          "default": true
        },
        "notifySms": {
          "name": "notifySms",
          "type": "boolean",
          "primaryKey": false,
          "notNull": true,
          "autoincrement": false,
          "default": false
        },
        "dpaConsent": {
          "name": "dpaConsent",
          "type": "boolean",
          "primaryKey": false,
          "notNull": true,
          "autoincrement": false,
          "default": false
        },
        "dpaConsentAt": {
          "name": "dpaConsentAt",
          "type": "timestamp",
          "primaryKey": false,
          "notNull": false,
          "autoincrement": false
        },
        "createdAt": {
          "name": "createdAt",
          "type": "timestamp",
          "primaryKey": false,
          "notNull": true,
          "autoincrement": false,
          "default": "(now())"
        },
        "updatedAt": {
          "name": "updatedAt",
          "type": "timestamp",
          "primaryKey": false,
          "notNull": true,
          "autoincrement": false,
          "onUpdate": true,
          "default": "(now())"
        },
        "lastSignedIn": {
          "name": "lastSignedIn",
          "type": "timestamp",
          "primaryKey": false,
          "notNull": true,
          "autoincrement": false,
          "default": "(now())"
        }
      },
      "indexes": {},
      "foreignKeys": {},
      "compositePrimaryKeys": {
        "users_id": {
          "name": "users_id",
          "columns": [
            "id"
          ]
        }
      },
      "uniqueConstraints": {
        "users_openId_unique": {
          "name": "users_openId_unique",
          "columns": [
            "openId"
          ]
        }
      },
      "checkConstraint": {}
    }
  },
  "views": {},
  "_meta": {
    "schemas": {},
    "tables": {},
    "columns": {}
  },
  "internal": {
    "tables": {},
    "indexes": {}
  }
}